gnocis/MOCCAModels.py
gnocis/__init__.py
gnocis/about.py
gnocis/biomarkers.cpython-38-darwin.so
gnocis/common.cpython-38-darwin.so
gnocis/curves.cpython-38-darwin.so
gnocis/featurenetwork.cpython-38-darwin.so
gnocis/features.cpython-38-darwin.so
gnocis/genome.py
gnocis/ioputil.py
gnocis/models.cpython-38-darwin.so
gnocis/motifs.cpython-38-darwin.so
gnocis/regions.cpython-38-darwin.so
gnocis/sequences.cpython-38-darwin.so
gnocis/sklearnCUDAModels.py
gnocis/sklearnModels.py
gnocis/sklearnModelsOpt.py
gnocis/tfModels.py
gnocis/validation.cpython-38-darwin.so
gnocis-0.9.12.dist-info/LICENSE
gnocis-0.9.12.dist-info/METADATA
gnocis-0.9.12.dist-info/WHEEL
gnocis-0.9.12.dist-info/top_level.txt
gnocis-0.9.12.dist-info/RECORD
