Metadata-Version: 2.1
Name: gnocis
Version: 0.9.12
Summary: Gnocis is a system for the analysis and the modelling of cis-regulatory DNA sequences.
Home-page: https://github.com/bjornbredesen/gnocis
Author: BjÃ¸rn AndrÃ© Bredesen-Aa
Author-email: bjorn@bjornbredesen.no
License: MIT
Platform: UNKNOWN
Classifier: Development Status :: 4 - Beta
Classifier: Environment :: Console
Classifier: Intended Audience :: Developers
Classifier: Intended Audience :: Information Technology
Classifier: License :: OSI Approved :: MIT License
Classifier: Operating System :: POSIX :: Linux
Classifier: Operating System :: Microsoft :: Windows
Classifier: Operating System :: MacOS
Classifier: Programming Language :: Cython
Classifier: Programming Language :: Python :: 3.6
Classifier: Programming Language :: Python :: 3.7
Classifier: Programming Language :: Python :: 3.8
Classifier: Programming Language :: Python :: 3.9
Classifier: Topic :: Scientific/Engineering
Classifier: Topic :: Scientific/Engineering :: Bio-Informatics
